{
  "category": "货物类",
  "items": [
    {
      "title": "兰州交通大学2026年军训服采购项目公开招标公告",
      "url": "https://zbzx.lzjtu.edu.cn/info/10446/89194.htm",
      "date": "2026年06月17日"
    },
    {
      "title": "兰州交通大学南苑学生公寓宿舍门更换项目招标公告",
      "url": "https://zbzx.lzjtu.edu.cn/info/10446/89193.htm",
      "date": "2026年06月17日"
    },
    {
      "title": "兰州交通大学2026级入校新生校徽定制项目招标公告",
      "url": "https://zbzx.lzjtu.edu.cn/info/10446/89169.htm",
      "date": "2026年06月11日"
    },
    {
      "title": "兰州交通大学档案馆档案信息化建设项目招标公告",
      "url": "https://zbzx.lzjtu.edu.cn/info/10446/89164.htm",
      "date": "2026年06月09日"
    },
    {
      "title": "兰州交通大学医院急救设备采购项目招标公告",
      "url": "https://zbzx.lzjtu.edu.cn/info/10446/89163.htm",
      "date": "2026年06月09日"
    },
    {
      "title": "兰州交通大学拼接四轮足机器人采购项目（二次）招标公告",
      "url": "https://zbzx.lzjtu.edu.cn/info/10446/89145.htm",
      "date": "2026年06月05日"
    },
    {
      "title": "兰州交通大学实验室危险废物和危险化学品库房改建项目(二期)招标公告",
      "url": "https://zbzx.lzjtu.edu.cn/info/10446/89123.htm",
      "date": "2026年05月29日"
    },
    {
      "title": "兰州交通大学图书馆（天佑美术馆）改造提升项目-LED小间距大屏采购安装项目招标公告",
      "url": "https://zbzx.lzjtu.edu.cn/info/10446/89120.htm",
      "date": "2026年05月28日"
    },
    {
      "title": "兰州交通大学拼接四轮足机器人采购项目招标公告",
      "url": "https://zbzx.lzjtu.edu.cn/info/10446/89106.htm",
      "date": "2026年05月25日"
    },
    {
      "title": "兰州交通大学附属中学校服购置服务商遴选项目（二次） 遴选公告",
      "url": "https://zbzx.lzjtu.edu.cn/info/10446/89105.htm",
      "date": "2026年05月25日"
    },
    {
      "title": "兰州交通大学后勤保障部2026年清扫工具、清洁用品、劳保用品采购项目招标公告",
      "url": "https://zbzx.lzjtu.edu.cn/info/10446/89104.htm",
      "date": "2026年05月25日"
    }
  ],
  "total": 11
}